README.txt
setup.py
apidocs/__init__.py
mopowg/__init__.py
mopowg/mopowg.py
mopowg/release.py
mopowg.egg-info/PKG-INFO
mopowg.egg-info/SOURCES.html
mopowg.egg-info/SOURCES.txt
mopowg.egg-info/dependency_links.html
mopowg.egg-info/dependency_links.txt
mopowg.egg-info/entry_points.html
mopowg.egg-info/entry_points.txt
mopowg.egg-info/not-zip-safe
mopowg.egg-info/requires.html
mopowg.egg-info/requires.txt
mopowg.egg-info/style.css
mopowg.egg-info/top_level.html
mopowg.egg-info/top_level.txt
