Metadata-Version: 1.0
Name: mopowg
Version: 0.2.1.1
Summary: Doc generator with styles, and syntax highlighting blocks
Home-page: http://hg.python.org.tw/mopowg
Author: Fred Lin
Author-email: gasolin@gmail.com
License: MIT <http://www.opensource.org/licenses/mit-license.php>
Download-URL: http://hg.python.org.tw/mopowg
Platform: UNKNOWN
Classifier: Development Status :: 3 - Alpha
Classifier: Environment :: Console
Classifier: Intended Audience :: Developers
Classifier: License :: OSI Approved :: MIT License
Classifier: Operating System :: OS Independent
Classifier: Programming Language :: Python
Classifier: Topic :: Software Development :: Libraries :: Python Modules
